CHANGELOG.md
README.md
motor-stubs/__init__.pyi
motor-stubs/core.pyi
motor-stubs/metaprogramming.py
motor-stubs/motor_asyncio.pyi
motor_stubs-1.7.1.dist-info/LICENSE
motor_stubs-1.7.1.dist-info/WHEEL
motor_stubs-1.7.1.dist-info/METADATA
motor_stubs-1.7.1.dist-info/RECORD
