Metadata-Version: 2.1
Name: motor-stubs
Version: 1.7.1
Summary: 
Home-page: https://github.com/Yian8068/motor-stubs.git
Keywords: mongo,motor,motor-stubs
Author: Daniel Hsiao
Author-email: yian8068@yahoo.com.tw
Requires-Python: >=3.9,<4.0
Classifier: Programming Language :: Python :: 3
Classifier: Programming Language :: Python :: 3.10
Classifier: Programming Language :: Python :: 3.9
Project-URL: Repository, https://github.com/Yian8068/motor-stubs.git
